//
// Created by Sergey Kuznetsov on 2018-10-07.
// Copyright (c) 2018 IT Erudit, Inc. All rights reserved.
//

import Foundation

public enum JavaOps: UInt8 {
    case OP_nop = 0x00
    case OP_aconst_null = 0x01
    case OP_iconst_m1 = 0x02
    case OP_iconst_0 = 0x03
    case OP_iconst_1 = 0x04
    case OP_iconst_2 = 0x05
    case OP_iconst_3 = 0x06
    case OP_iconst_4 = 0x07
    case OP_iconst_5 = 0x08
    case OP_lconst_0 = 0x09
    case OP_lconst_1 = 0x0A
    case OP_fconst_0 = 0x0B
    case OP_fconst_1 = 0x0C
    case OP_fconst_2 = 0x0D
    case OP_dconst_0 = 0x0E
    case OP_dconst_1 = 0x0F
    case OP_bipush = 0x10
    case OP_sipush = 0x11
    case OP_ldc = 0x12
    case OP_ldc_w = 0x13
    case OP_ldc2_w = 0x14
    case OP_iload = 0x15
    case OP_lload = 0x16
    case OP_fload = 0x17
    case OP_dload = 0x18
    case OP_aload = 0x19
    case OP_iload_0 = 0x1A
    case OP_iload_1 = 0x1B
    case OP_iload_2 = 0x1C
    case OP_iload_3 = 0x1D
    case OP_lload_0 = 0x1E
    case OP_lload_1 = 0x1F
    case OP_lload_2 = 0x20
    case OP_lload_3 = 0x21
    case OP_fload_0 = 0x22
    case OP_fload_1 = 0x23
    case OP_fload_2 = 0x24
    case OP_fload_3 = 0x25
    case OP_dload_0 = 0x26
    case OP_dload_1 = 0x27
    case OP_dload_2 = 0x28
    case OP_dload_3 = 0x29
    case OP_aload_0 = 0x2A
    case OP_aload_1 = 0x2B
    case OP_aload_2 = 0x2C
    case OP_aload_3 = 0x2D
    case OP_iaload = 0x2E
    case OP_laload = 0x2F
    case OP_faload = 0x30
    case OP_daload = 0x31
    case OP_aaload = 0x32
    case OP_baload = 0x33
    case OP_caload = 0x34
    case OP_saload = 0x35
    case OP_istore = 0x36
    case OP_lstore = 0x37
    case OP_fstore = 0x38
    case OP_dstore = 0x39
    case OP_astore = 0x3A
    case OP_istore_0 = 0x3B
    case OP_istore_1 = 0x3C
    case OP_istore_2 = 0x3D
    case OP_istore_3 = 0x3E
    case OP_lstore_0 = 0x3F
    case OP_lstore_1 = 0x40
    case OP_lstore_2 = 0x41
    case OP_lstore_3 = 0x42
    case OP_fstore_0 = 0x43
    case OP_fstore_1 = 0x44
    case OP_fstore_2 = 0x45
    case OP_fstore_3 = 0x46
    case OP_dstore_0 = 0x47
    case OP_dstore_1 = 0x48
    case OP_dstore_2 = 0x49
    case OP_dstore_3 = 0x4A
    case OP_astore_0 = 0x4B
    case OP_astore_1 = 0x4C
    case OP_astore_2 = 0x4D
    case OP_astore_3 = 0x4E
    case OP_iastore = 0x4F
    case OP_lastore = 0x50
    case OP_fastore = 0x51
    case OP_dastore = 0x52
    case OP_aastore = 0x53
    case OP_bastore = 0x54
    case OP_castore = 0x55
    case OP_sastore = 0x56
    case OP_pop = 0x57
    case OP_pop2 = 0x58
    case OP_dup = 0x59
    case OP_dup_x1 = 0x5A
    case OP_dup_x2 = 0x5B
    case OP_dup2 = 0x5C
    case OP_dup2_x1 = 0x5D
    case OP_dup2_x2 = 0x5E
    case OP_swap = 0x5F
    case OP_iadd = 0x60
    case OP_ladd = 0x61
    case OP_fadd = 0x62
    case OP_dadd = 0x63
    case OP_isub = 0x64
    case OP_lsub = 0x65
    case OP_fsub = 0x66
    case OP_dsub = 0x67
    case OP_imul = 0x68
    case OP_lmul = 0x69
    case OP_fmul = 0x6A
    case OP_dmul = 0x6B
    case OP_idiv = 0x6C
    case OP_ldiv = 0x6D
    case OP_fdiv = 0x6E
    case OP_ddiv = 0x6F
    case OP_irem = 0x70
    case OP_lrem = 0x71
    case OP_frem = 0x72
    case OP_drem = 0x73
    case OP_ineg = 0x74
    case OP_lneg = 0x75
    case OP_fneg = 0x76
    case OP_dneg = 0x77
    case OP_ishl = 0x78
    case OP_lshl = 0x79
    case OP_ishr = 0x7A
    case OP_lshr = 0x7B
    case OP_iushr = 0x7C
    case OP_lushr = 0x7D
    case OP_iand = 0x7E
    case OP_land = 0x7F
    case OP_ior = 0x80
    case OP_lor = 0x81
    case OP_ixor = 0x82
    case OP_lxor = 0x83
    case OP_iinc = 0x84
    case OP_i2l = 0x85
    case OP_i2f = 0x86
    case OP_i2d = 0x87
    case OP_l2i = 0x88
    case OP_l2f = 0x89
    case OP_l2d = 0x8A
    case OP_f2i = 0x8B
    case OP_f2l = 0x8C
    case OP_f2d = 0x8D
    case OP_d2i = 0x8E
    case OP_d2l = 0x8F
    case OP_d2f = 0x90
    case OP_i2b = 0x91
    case OP_i2c = 0x92
    case OP_i2s = 0x93
    case OP_lcmp = 0x94
    case OP_fcmpl = 0x95
    case OP_fcmpg = 0x96
    case OP_dcmpl = 0x97
    case OP_dcmpg = 0x98
    case OP_ifeq = 0x99
    case OP_ifne = 0x9A
    case OP_iflt = 0x9B
    case OP_ifge = 0x9C
    case OP_ifgt = 0x9D
    case OP_ifle = 0x9E
    case OP_if_icmpeq = 0x9F
    case OP_if_icmpne = 0xA0
    case OP_if_icmplt = 0xA1
    case OP_if_icmpge = 0xA2
    case OP_if_icmpgt = 0xA3
    case OP_if_icmple = 0xA4
    case OP_if_acmpeq = 0xA5
    case OP_if_acmpne = 0xA6
    case OP_goto = 0xA7
    case OP_jsr = 0xA8
    case OP_ret = 0xA9
    case OP_tableswitch = 0xAA
    case OP_lookupswitch = 0xAB
    case OP_ireturn = 0xAC
    case OP_lreturn = 0xAD
    case OP_freturn = 0xAE
    case OP_dreturn = 0xAF
    case OP_areturn = 0xB0
    case OP_return = 0xB1
    case OP_getstatic = 0xB2
    case OP_putstatic = 0xB3
    case OP_getfield = 0xB4
    case OP_putfield = 0xB5
    case OP_invokevirtual = 0xB6
    case OP_invokespecial = 0xB7
    case OP_invokestatic = 0xB8
    case OP_invokeinterface = 0xB9
    case OP_invokedynamic = 0xBA
    case OP_new = 0xBB
    case OP_newarray = 0xBC
    case OP_anewarray = 0xBD
    case OP_arraylength = 0xBE
    case OP_athrow = 0xBF
    case OP_checkcast = 0xC0
    case OP_instanceof = 0xC1
    case OP_monitorenter = 0xC2
    case OP_monitorexit = 0xC3
    case OP_wide = 0xC4
    case OP_multianewarray = 0xC5
    case OP_ifnull = 0xC6
    case OP_ifnonnull = 0xC7
    case OP_goto_w = 0xC8
    case OP_jsr_w = 0xC9
}

public enum AccessType: UInt32 {
    case PUBLIC = 0x0001
    case PRIVATE = 0x0002
    case PROTECTED = 0x0004
    case STATIC = 0x0008
    case FINAL = 0x0010
    case SYNCHRONIZED = 0x0020
    case VOLATILE = 0x0040
    case TRANSIENT = 0x0080
    case NATIVE = 0x0100
    case INTERFACE = 0x0200
    case ABSTRACT = 0x0400
}

public enum AttributeType: String {
    case ConstantValue = "ConstantValue"
    case Code = "Code"
    case Exceptions = "Exceptions"
    case InnerClasses = "InnerClasses"
    case Synthetic = "Synthetic"
    case SourceFile = "SourceFile"
    case LineNumberTable = "LineNumberTable"
    case LocalVariableTable = "LocalVariableTable"
    case MethodParameters = "MethodParameters"
    case Signature = "Signature"
    case BootstrapMethods = "BootstrapMethods"
    case RuntimeVisibleAnnotations = "RuntimeVisibleAnnotations"
    case RuntimeInvisibleAnnotations = "RuntimeInvisibleAnnotations"
    case RuntimeVisibleParameterAnnotations = "RuntimeVisibleParameterAnnotations"
    case RuntimeInvisibleParameterAnnotations = "RuntimeInvisibleParameterAnnotations"
    case EnclosingMethod = "EnclosingMethod"
    case AnnotationDefault = "AnnotationDefault"
    case Deprecated = "Deprecated"
}

public enum ConstantType: UInt8 {
    case Class = 7
    case Fieldref = 9
    case Methodref = 10
    case InterfaceMethodref = 11
    case String = 8
    case Integer = 3
    case Float = 4
    case Long = 5
    case Double = 6
    case NameAndType = 12
    case Utf8 = 1
    case MethodHandle = 15
    case MethodType = 16
    case InvokeDynamic = 18
    case Module = 19
    case Package = 2
}

public enum RefType: UInt8 {
    case GetField = 1
    case GetStatic = 2
    case PutField = 3
    case PutStatic = 4
    case InvokeVirtual = 5
    case InvokeStatic = 6
    case InvokeSpecial = 7
    case NewInvokeSpecial = 8
    case InvokeInterface = 9
}